promcat/__init__.py
promcat/cli.py
promcat-0.1.3.dist-info/METADATA
promcat-0.1.3.dist-info/WHEEL
promcat-0.1.3.dist-info/entry_points.txt
promcat-0.1.3.dist-info/licenses/LICENSE
promcat-0.1.3.dist-info/RECORD
