Metadata-Version: 2.4
Name: promcat
Version: 0.1.3
Summary: Concatenate all text files in a directory and its subdirectories
Project-URL: Repository, https://github.com/jangop/promcat.git
Project-URL: Issues, https://github.com/jangop/promcat/issues
Author-email: Jan Philip Göpfert <janphilip@gopfert.eu>
License-File: LICENSE
Requires-Python: >=3.12
Requires-Dist: click>=8.0.0
Requires-Dist: loguru>=0.7.2
Requires-Dist: pathspec>=0.12.1
Provides-Extra: dev
Requires-Dist: pytest>=8.0.0; extra == 'dev'
